Metadata-Version: 2.1
Name: novicedude-cli
Version: 1.2.0
Summary: SingularityNET CLI
Home-page: https://github.com/singnet/snet-cli
Author: SingularityNET Foundation
Author-email: info@singularitynet.io
License: MIT
Platform: UNKNOWN
Requires-Python: >=3.6
Requires-Dist: grpcio-tools (==1.19.0)
Requires-Dist: jsonrpcclient (==2.5.2)
Requires-Dist: web3 (==4.8.3)
Requires-Dist: mnemonic (==0.18)
Requires-Dist: pycoin (==0.80)
Requires-Dist: rlp (==1.0.1)
Requires-Dist: pyyaml (==4.2b1)
Requires-Dist: ipfsapi (==0.4.2.post1)
Requires-Dist: rfc3986 (==1.1.0)
Requires-Dist: pymultihash (==0.8.2)
Requires-Dist: base58 (==1.0.2)
Requires-Dist: argcomplete (==1.9.4)
Requires-Dist: grpcio-health-checking (==1.19.0)
Requires-Dist: trezor (==0.9.1)
Requires-Dist: ledgerblue (==0.1.27)
